README.md
setup.py
numpy_partition.egg-info/PKG-INFO
numpy_partition.egg-info/SOURCES.txt
numpy_partition.egg-info/dependency_links.txt
numpy_partition.egg-info/requires.txt
numpy_partition.egg-info/top_level.txt
partition/__init__.py
partition/partition.py
partition/window.py