Metadata-Version: 2.1
Name: numpy-partition
Version: 1.18.7
Summary: SQL PARTITION BY and window functions for NumPy
Home-page: https://github.com/
Author: partitionby
Author-email: partitionby@protonmail.ch
License: UNKNOWN
Platform: UNKNOWN
Classifier: Operating System :: OS Independent
Classifier: License :: OSI Approved :: MIT License
Classifier: Programming Language :: Python :: 3
